{
    "results":[
       {
          "title":"ENGLISH 2023 YEAR PAPER",
          "url":"https://drive.google.com/file/d/1DOijQ4NRyLpbXqIE2Tl-ciDnxoM-hnEV/view?usp=sharing"
       },
      
       {
          "title":"ENGLISH 2021 YEAR PAPER",
          "url":"https://drive.google.com/file/d/1DAUzMlnFy9ZJQpt0Z6_IieG1rvSIgm32/view?usp=sharing"
       },
       {
          "title":"ENGLISH 2020 YEAR PAPER",
          "url":"https://drive.google.com/file/d/1DAVL0UFBNPNL6i4QYr9v9oXGDAxzGp9Q/view?usp=sharing"
       },
       {
          "title":"ENGLISH 2020 YEAR PAPER 1A",
          "url":"https://drive.google.com/file/d/1DELzKCyCbYGNVv8JSQd7Urlq3XDCnvcX/view?usp=sharing"
       },
       {
          "title":"ENGLISH 2020 YEAR PAPER 2C",
          "url":"https://drive.google.com/file/d/1DI0juFBPkZhlqjnAKouKmVTHJ_K7gjg7/view?usp=sharing"
       },
       {
          "title":"ENGLISH 2020 YEAR PAPER 3D",
          "url":"https://drive.google.com/file/d/1D8ELLZo39P662DqP3cqzz8RtBXEvgw2d/view?usp=sharing"
       },
       {
          "title":"ENGLISH 2020 YEAR PAPER 4A",
          "url":"https://drive.google.com/file/d/1Cv6yp7BW61qNIWD6ptbxeJpOyjYVtbqv/view?usp=sharing"
       },
       
       {
          "title":"ENGLISH 2020 YEAR PAPER 5C",
          "url":"https://drive.google.com/file/d/1D2kCIkuHNM_5YDITXiFXZu9PArPo4DFd/view?usp=sharing"
       },
       {
          "title":"ENGLISH 2019 YEAR PAPER 1A",
          "url":"https://drive.google.com/file/d/1D5PaZKxlhDkkkUlHEom0cH4YKCXiU8b8/view?usp=sharing"
       },
       {
          "title":"ENGLISH 2019 YEAR PAPER 2B",
          "url":"https://drive.google.com/file/d/1A9IBfEQG_-apTXp7pkzaLidFSkTFeqac/view?usp=sharing"
       },
      {
          "title":"ENGLISH 2019 YEAR PAPER 3C",
          "url":"https://drive.google.com/file/d/1ANNyZtZqIeQVLFp9zOK-6lp_p7bin1uS/view?usp=sharing"
       },
       {
          "title":"ENGLISH 2019 YEAR PAPER 4D",
          "url":"https://drive.google.com/file/d/19pVqx8zJoSR-NHrKGdMwazWaL_aDMT44/view?usp=sharing"
       },
       {
          "title":"ENGLISH 2019 YEAR PAPER 5A",
          "url":"https://drive.google.com/file/d/1AVOG_t2WPOUQI_J4yKJb8zDr-gNfA1dK/view?usp=sharing"
       },
       {
          "title":"ENGLISH 2019 YEAR PAPER 6B",
          "url":"https://drive.google.com/file/d/1AZiDeozJMsT0Lg3_Eu7jum8iz7T7l9sF/view?usp=sharing"
       },
       {
          "title":"ENGLISH 2019 YEAR PAPER 7C",
          "url":"https://drive.google.com/file/d/1Ag5HzMIOB3Y6xOpr6A5NrMLwYnWGS_mu/view?usp=sharing"
       },
       {
          "title":"ENGLISH 2019 YEAR PAPER 8D",
          "url":"https://drive.google.com/file/d/1AjaIEdiWR5f0l1iWS8rNNlkizXyg9HiA/view?usp=sharing"
       },
       {
          "title":"ENGLISH 2019 YEAR PAPER 9A",
          "url":"https://drive.google.com/file/d/1AoNuLvW1e4HDjQXpwwjhhhdB2de1RkRl/view?usp=sharing"
       },
       {
          "title":"ENGLISH 2018 YEAR PAPER 1",
          "url":"https://drive.google.com/file/d/19hnThlcTz2VcXagWk9SbXS35SPpWsT4e/view?usp=sharing"
       },
       {
          "title":"ENGLISH 2018 YEAR PAPER 2",
          "url":"https://drive.google.com/file/d/19ljlU01rE_AVYB6TPeVXIKUtdOEfVBUq/view?usp=sharing"
       },
       {
          "title":"ENGLISH 2018 YEAR PAPER 3",
          "url":"https://drive.google.com/file/d/19n2Efre48sibPVhIRuOiWtvmQcDcA21K/view?usp=sharing"
       },
       {
          "title":"ENGLISH 2018 YEAR PAPER 5B",
          "url":"https://drive.google.com/file/d/1A3IRDUq1SS33xS7_i0hx6Vbpl27aSZrc/view?usp=sharing"
       },
       {
          "title":"ENGLISH 2017 YEAR PAPER",
          "url":"https://drive.google.com/file/d/19_VQoOs7JveuSyI4CeHja2bLgXMzcWLa/view?usp=sharing"
       },
       {
          "title":"ENGLISH 2016 YEAR PAPER",
          "url":"https://drive.google.com/file/d/19Kkat_ezE2xyyEm7rsLxCT1C3B3iZ1z7/view?usp=sharing"
       },
       {
          "title":"ENGLISH 2015 YEAR PAPER",
          "url":"https://drive.google.com/file/d/19JC2iei469iqHVJ3bTkeXwtCmv81xZZt/view?usp=sharing"
       }      
    ]
 }
