
{
    "results": [
        {
            "Bio1e16": "",
            "Bio1t16": "",
            "Che1e16": "",
            "Che1t16": "",
            "Civ116": "",
            "Commer116": "",
            "Eng116": "",
            "Eco116": "",
            "Hin116": "",
            "His116": "",
            "M1ae16": "",
            "M1at16": "",
            "M1be16": "",
            "M1bt16": "",
            "Pht1e16": "",
            "Pht1t16": "",
            "Pol116": "",
            "San116": "",
            "Tel116": "",
            "Zol1e16": "",
            "Zol1t16": ""
        }
    ]
}
