 {
    "results": [
       {
            "question": "The sum of first 100 natural numbers is?(OR)మొదటి 100 సహజ సంఖ్యల మొత్తం",
            "incorrect_answers": [
                "4050",
                "4500",
                "5500"
            ],
            "correct_answer": "5050"
        },
        {
            "question": "2.If 16, x, 36 are in G.P. then x =?(or)16, x, 36 GPలో ఉంటే x =",
            "incorrect_answers": [
                "28",
                "30",
              "26"
            ],
            "correct_answer": "24"
        },
        {
            "question": "3.The next term of the A.P(a + 3d),(a + d). (a – d), ………….. is?(OR)AP(a + 3d),(a + d) యొక్క తదుపరి పదం.(a – d), …………….. ఉంది?",
            "a + 2d",
                " a - 2d",
              "a – 4d"
            ],
            "correct_answer": "a – 3d"
        },
        {
            "question": "4. Which of the following is not a basic function ??(OR)కింది వాటిలో ఏది ప్రాథమిక విధి కాదు?",
            "incorrect_answers": [
                " Movement(OR)ఉద్యమం",
                "Control of hormones(0R)హార్మోన్ల నియంత్రణ",
              "Co-ordination(OR)సమన్వయ"
            ],
            "correct_answer": "Balance(OR)సంతులనం"
        },
        {
            "question": "5.Nissil’s granules are present in?(OR)నిస్సిల్ యొక్క కణికలు ఉన్నాయిు?",
            "incorrect_answers": [
                " Eosinophils(OR)ఇసినోఫిల్స్",
                "Neutrophils(OR)న్యూట్రోఫిల్స్",
              "Lymphocytes(OR)లింఫోసైట్లు"
            ],
            "correct_answer": "Cyton(OR)సైటన్"
        },
        {
            "question": "6.Nervous system starts from …………………. part.?(Or)నాడీ వ్యవస్థ ………………. భాగం?",
            "incorrect_answers": [
                "A.Brain(OR)మెదడు",
                "B.Spinal cord(OR) వెన్ను ఎముక",
              "C.Heart(OR)గుండె"
            ],
            "correct_answer": "A and B"
        }
      
    ]
}
