{
    "results": [
    {
            "question": "1.The highest peak in Eastern Ghats?(or)తూర్పు కనుమలలో ఎత్తైన శిఖరం?",
         "incorrect_answers": [
                "Gursikhar",
                "DodaBetta",
                "Anaimudi"
            ],
            "correct_answer": "Aroya Kondat"
        },

       {
            "question": "2.The latitude that does NOT pass through India.?(OR)భారతదేశం గుండా వెళ్ళని అక్షాంశం.?",
            "incorrect_answers": [
                "36° N.L.e",
                " 12° N.L.",
                "8° N.L."
            ],
            "correct_answer": "48° N.L."
        },

        {
           "question": "3.The latitude that passes through India?(OR)భారతదేశం గుండా వెళుతున్న అక్షాంశం?",
             "incorrect_answers": [
               " Equator",
                " Tropic of Capricorn",
                "36°N"
            ],
            "correct_answer": "Tropic of Cancer"
        },

        {
            "question": "4.The difference between the Greenwich Mean Time and the Indian Standard Time is? (OR)గ్రీన్విచ్ మీన్ టైమ్ మరియు ఇండియన్ స్టాండర్డ్ టైమ్ మధ్య వ్యత్యాసం?",
          "incorrect_answers": [
               "+4.30 minutes",
                "-5.30 minutes",
                "-4.30 minutes"
            ],
            "correct_answer": "+ 5.30 minutes"
        },
        {
            "question": "5.The distance between North and South extremes of India is …………………?(OR)భారతదేశం యొక్క ఉత్తర మరియు దక్షిణ తీవ్రతల మధ్య దూరం ………………………?",
           "incorrect_answers": [
                " 2933 kms",
                "15,200 kms",
                " 7516.6 kms"
            ],
            "correct_answer": "3214 kms"
        },
        { "question": "6.The Pirpanjal ranges are situated in this region.?(OR)పిర్పంజల్ శ్రేణులు ఈ ప్రాంతంలో ఉన్నాయి.?",
             "incorrect_answers": [
               " Greater Himalayas",
                "Shivalik ranges",
                "Purvanchal"
            ],
            "correct_answer": " Lesser Himalayas"


        }
    ]
}
